primelab/__init__.py
primelab/__version__.py
primelab/dglobal.py
primelab/differentiation.py
primelab/dlocal.py
primelab/utils.py
primelab-0.1.2.dist-info/WHEEL
primelab-0.1.2.dist-info/METADATA
primelab-0.1.2.dist-info/RECORD
