Metadata-Version: 2.1
Name: primelab
Version: 0.1.2
Summary: Numerical differentiation in python.
Home-page: https://github.com/andgoldschmidt/primelab
License: MIT
Keywords: differentiation,derivative,gradient,prime
Author: Andy Goldschmidt
Author-email: andygold@uw.edu
Requires-Python: >=3.7,<4.0
Classifier: License :: OSI Approved :: MIT License
Classifier: Programming Language :: Python :: 3
Classifier: Programming Language :: Python :: 3.7
Classifier: Programming Language :: Python :: 3.8
Provides-Extra: docs
Requires-Dist: ipykernel (>=5.2.1,<6.0.0); extra == "docs"
Requires-Dist: jupyter_client (>=6.1.3,<7.0.0); extra == "docs"
Requires-Dist: nbsphinx (>=0.6.1,<0.7.0); extra == "docs"
Requires-Dist: numpy (>=1.18.3,<2.0.0)
Requires-Dist: scipy (>=1.4.1,<2.0.0)
Requires-Dist: sklearn (>=0.0,<0.1)
Requires-Dist: sphinx (>=3.0.2,<4.0.0); extra == "docs"
Project-URL: Documentation, https://prime.readthedocs.io/
Project-URL: Repository, https://github.com/andgoldschmidt/primelab
